[
  {
    "id": "os_1776768802792_fb912461",
    "type": "office-schedule",
    "uploadedAt": "2026-04-21T10:53:22.822Z",
    "memo": "오홍택/오승민",
    "summary": "주말뉴스 · 2026-04-26 18:00-21:00",
    "details": {
      "title": "주말뉴스",
      "program": "주말뉴스",
      "scheduleType": "office",
      "entries": [
        {
          "date": "2026-04-26",
          "time": "18:00-21:00",
          "place": "뉴스센터",
          "note": "오홍택/오승민"
        }
      ]
    }
  },
  {
    "id": "os_1776768035411_b2b2bc87",
    "type": "office-schedule",
    "uploadedAt": "2026-04-21T10:40:35.441Z",
    "memo": "테스트일정 월요일 · 2026-04-27",
    "summary": "테스트일정 월요일 · 2026-04-27",
    "details": {
      "title": "테스트일정 월요일",
      "program": "테스트일정 월요일",
      "scheduleType": "office",
      "entries": [
        {
          "date": "2026-04-27"
        }
      ]
    }
  },
  {
    "id": "os_1776768000812_1fd8c613",
    "type": "office-schedule",
    "uploadedAt": "2026-04-21T10:40:00.813Z",
    "memo": "테스트일정 월요일 · 2026-04-20",
    "summary": "테스트일정 월요일 · 2026-04-20",
    "details": {
      "title": "테스트일정 월요일",
      "program": "테스트일정 월요일",
      "scheduleType": "office",
      "entries": [
        {
          "date": "2026-04-20"
        }
      ]
    }
  }
]